pylogserver_aquanjsw/__init__.py
pylogserver_aquanjsw/main.py
pylogserver_aquanjsw-0.0.5.dist-info/METADATA
pylogserver_aquanjsw-0.0.5.dist-info/WHEEL
pylogserver_aquanjsw-0.0.5.dist-info/entry_points.txt
pylogserver_aquanjsw-0.0.5.dist-info/licenses/LICENSE
pylogserver_aquanjsw-0.0.5.dist-info/RECORD
