Metadata-Version: 2.3
Name: pylogserver_aquanjsw
Version: 0.0.5
Summary: A simple python logging server
Project-URL: Homepage, https://github.com/AquanJSW/packaging_pylogserver
Author-email: aquanjsw <zhdlcc@gmail.com>
License-File: LICENSE
Classifier: Operating System :: OS Independent
Classifier: Programming Language :: Python :: 3
Requires-Python: >=3.0
